data_v1/__init__.py
data_v1/complexfuncbench/complexfuncbench-data.json
data_v1/complexfuncbench/complexfuncbench-spec.json
data_v1/executable/executable-data.json
data_v1/executable/executable-spec.json
data_v1/executable/open_api_specs/Alpha_Vantage_CURRENCY_EXCHANGE_RATE.json
data_v1/executable/open_api_specs/CipherCircuit_Math_Assistant_CalculateAllArithmeticOperations.json
data_v1/executable/open_api_specs/Get_Country_Details_By_Country_Name.json
data_v1/executable/open_api_specs/Goodreads_Get_Authors_Books.json
data_v1/executable/open_api_specs/Goodreads_Search_Book_By_Keyword.json
data_v1/executable/open_api_specs/Goodreads_Search_Quotes_By_Keyword.json
data_v1/executable/open_api_specs/Instagram_Followers.json
data_v1/executable/open_api_specs/Instagram_Following.json
data_v1/executable/open_api_specs/Instagram_Info.json
data_v1/executable/open_api_specs/Instagram_Posts_Reels.json
data_v1/executable/open_api_specs/Instagram_Search_User.json
data_v1/executable/open_api_specs/LocalBusinessData.json
data_v1/executable/open_api_specs/LocalBusinessDataBusinessReviews.json
data_v1/executable/open_api_specs/NewsAPISearchByKeyWord.json
data_v1/executable/open_api_specs/Real-Time_Product_Search_Product_Details.json
data_v1/executable/open_api_specs/Real-Time_Product_Search_Product_Offers.json
data_v1/executable/open_api_specs/Real-Time_Product_Search_Product_Reviews.json
data_v1/executable/open_api_specs/Real-Time_Product_Search_Search.json
data_v1/executable/open_api_specs/RedditTopPostsBySubreddit.json
data_v1/executable/open_api_specs/SEC_Balance_Sheet.json
data_v1/executable/open_api_specs/SEC_Filings.json
data_v1/executable/open_api_specs/SEC_Financial_Statements_and_Disclosures.json
data_v1/executable/open_api_specs/SkyScrapperFlightSearch.json
data_v1/executable/open_api_specs/SkyScrapperSearchAirport.json
data_v1/executable/open_api_specs/Spotify_Scraper_Get_Artist_ID_By_Name.json
data_v1/executable/open_api_specs/Spotify_Scraper_Get_Artist_Overview.json
nestful_wrapper-0.1.7.dist-info/licenses/LICENSE
nestful_wrapper-0.1.7.dist-info/METADATA
nestful_wrapper-0.1.7.dist-info/WHEEL
nestful_wrapper-0.1.7.dist-info/top_level.txt
nestful_wrapper-0.1.7.dist-info/RECORD
