Metadata-Version: 2.4
Name: nestful-wrapper
Version: 0.1.7
Summary: A python wrapper over NESTFUL data
Author-email: Tathagata Chakraborti <tchakra2@ibm.com>
License:                                  Apache License
Project-URL: Repository, https://github.com/TathagataChakraborti/NESTFUL
Project-URL: Issues, https://github.com/TathagataChakraborti/NESTFUL/issues
Keywords: automated planning,natural language processing,process automation,service composition,conversational agents,generative ai,large language models
Classifier: Development Status :: 2 - Pre-Alpha
Classifier: Intended Audience :: Developers
Classifier: Intended Audience :: Science/Research
Classifier: Natural Language :: English
Classifier: License :: OSI Approved :: Apache Software License
Classifier: Operating System :: OS Independent
Classifier: Programming Language :: Python :: 3.11
Classifier: Framework :: Pydantic :: 2
Classifier: Topic :: Scientific/Engineering :: Artificial Intelligence
Classifier: Topic :: Scientific/Engineering :: Human Machine Interfaces
Classifier: Topic :: Scientific/Engineering :: Information Analysis
Classifier: Topic :: Software Development :: User Interfaces
Requires-Python: >=3.10
License-File: LICENSE
Requires-Dist: pydantic
Requires-Dist: jsonref
Requires-Dist: jmespath
Requires-Dist: hypothesis-jsonschema
Requires-Dist: Faker
Requires-Dist: genson
Requires-Dist: sentence-transformers
Requires-Dist: nltk
Requires-Dist: scipy
Requires-Dist: jsonschema
Requires-Dist: backports.strenum
Provides-Extra: dev
Requires-Dist: pytest; extra == "dev"
Requires-Dist: black; extra == "dev"
Requires-Dist: pylint; extra == "dev"
Requires-Dist: flake8; extra == "dev"
Requires-Dist: pre-commit; extra == "dev"
Requires-Dist: Flake8-pyproject; extra == "dev"
Dynamic: license-file
